ycsai/__init__.py
ycsai/cfg/__init__.py
ycsai/data/__init__.py
ycsai/data/augmentations.py
ycsai/data/dataloader.py
ycsai/layers/__init__.py
ycsai/layers/commons.py
ycsai/layers/modules.py
ycsai/models/__init__.py
ycsai/models/engines.py
ycsai/models/tasks.py
ycsai/utils/__init__.py
ycsai/utils/download.py
ycsai/utils/experiments.py
ycsai/utils/general.py
ycsai/utils/lion.py
ycsai/utils/loss.py
ycsai/utils/plots.py
ycsai/utils/torch_utils.py
ycsai/utils/val.py
YCSAI-1.0.1.dist-info/METADATA
YCSAI-1.0.1.dist-info/WHEEL
YCSAI-1.0.1.dist-info/top_level.txt
YCSAI-1.0.1.dist-info/RECORD
